pyrelimri/__init__.py
pyrelimri/brain_icc.py
pyrelimri/conn_icc.py
pyrelimri/icc.py
pyrelimri/masked_timeseries.py
pyrelimri/mktestdata.py
pyrelimri/similarity.py
pyrelimri/tetrachoric_correlation.py
pyrelimri-2.2.3.dist-info/licenses/LICENSE
pyrelimri-2.2.3.dist-info/METADATA
pyrelimri-2.2.3.dist-info/WHEEL
pyrelimri-2.2.3.dist-info/top_level.txt
pyrelimri-2.2.3.dist-info/RECORD
