Metadata-Version: 2.4
Name: PyReliMRI
Version: 2.2.3
Summary: A package for computing reliability of MRI/fMRI images
Home-page: https://github.com/demidenm/PyReliMRI
Author: Michael Demidenko
Author-email: demidenko.michael@gmail.com
License: MIT
Project-URL: Bug Tracker, https://github.com/demidenm/PyReliMRI/issues
Classifier: Development Status :: 4 - Beta
Classifier: Intended Audience :: Science/Research
Classifier: Topic :: Scientific/Engineering :: Medical Science Apps.
Classifier: Programming Language :: Python :: 3
Classifier: Programming Language :: Python :: 3.9
Classifier: Programming Language :: Python :: 3.10
Classifier: Programming Language :: Python :: 3.11
Classifier: License :: OSI Approved :: MIT License
Classifier: Operating System :: OS Independent
Requires-Python: >=3.9
License-File: LICENSE
Requires-Dist: numpy
Requires-Dist: pandas
Requires-Dist: nilearn
Requires-Dist: nibabel
Requires-Dist: scipy
Requires-Dist: seaborn
Requires-Dist: scikit-learn
Requires-Dist: hypothesis
Requires-Dist: matplotlib
Requires-Dist: joblib
Requires-Dist: statsmodels
Provides-Extra: dev
Requires-Dist: pytest; extra == "dev"
Requires-Dist: pytest-cov; extra == "dev"
Requires-Dist: black; extra == "dev"
Requires-Dist: flake8; extra == "dev"
Dynamic: author
Dynamic: author-email
Dynamic: classifier
Dynamic: description
Dynamic: description-content-type
Dynamic: home-page
Dynamic: license
Dynamic: license-file
Dynamic: project-url
Dynamic: provides-extra
Dynamic: requires-dist
Dynamic: requires-python
Dynamic: summary
